btobex/__init__.py
btobex/__main__.py
btobex/bluez_helper.py
btobex/client.py
btobex/common.py
btobex/headers.py
btobex/obex.py
btobex/obex_client.py
btobex/requests.py
btobex/responses.py
btobex/server.py
btobex/xml_helper.py
btobex/pytransform/__init__.py
btobex/pytransform/platforms/linux/aarch64/_pytransform.so
btobex/pytransform/platforms/linux/x86_64/_pytransform.so
btobex-0.0.1.dist-info/LICENSE.txt
btobex-0.0.1.dist-info/METADATA
btobex-0.0.1.dist-info/WHEEL
btobex-0.0.1.dist-info/entry_points.txt
btobex-0.0.1.dist-info/top_level.txt
btobex-0.0.1.dist-info/RECORD
