Metadata-Version: 2.1
Name: btobex
Version: 0.0.1
Summary: ...
Home-page: https://pypi.org/project/btobex
Author: Cibo
Author-email: cibo@bio-electric.com
Classifier: Operating System :: POSIX :: Linux
Classifier: Environment :: Console
Classifier: Programming Language :: Python :: 3
Classifier: Programming Language :: Python :: 3 :: Only
Classifier: Programming Language :: Python :: 3.10
Classifier: License :: Other/Proprietary License
Requires-Python: ==3.10.*
License-File: LICENSE.txt
Requires-Dist: btl2cap (>=0.0.11)
Requires-Dist: xpycommon (>=0.0.24)
